LICENSE
MANIFEST.in
README.rst
flask_gears.py
setup.py
Flask_Gears.egg-info/PKG-INFO
Flask_Gears.egg-info/SOURCES.txt
Flask_Gears.egg-info/dependency_links.txt
Flask_Gears.egg-info/requires.txt
Flask_Gears.egg-info/top_level.txt