Metadata-Version: 1.1
Name: Flask-Gears
Version: 0.2
Summary: Gears for Flask
Home-page: https://github.com/gears/flask-gears
Author: Mike Yumatov
Author-email: mike@yumatov.org
License: ISC
Platform: any
Classifier: Development Status :: 3 - Alpha
Classifier: Environment :: Web Environment
Classifier: Intended Audience :: Developers
Classifier: License :: OSI Approved :: ISC License (ISCL)
Classifier: Operating System :: OS Independent
Classifier: Programming Language :: Python
Classifier: Programming Language :: Python :: 2.6
Classifier: Programming Language :: Python :: 2.7
Classifier: Topic :: Internet :: WWW/HTTP
Classifier: Topic :: Software Development :: Libraries :: Python Modules
